Mortgage_calculator/__init__.py
mortgage_caLculator-0.1.dist-info/LICENCE.txt
mortgage_caLculator-0.1.dist-info/METADATA
mortgage_caLculator-0.1.dist-info/WHEEL
mortgage_caLculator-0.1.dist-info/top_level.txt
mortgage_caLculator-0.1.dist-info/RECORD
