Metadata-Version: 2.1
Name: mortgage-caLculator
Version: 0.1
Summary: calculate monthly payments for a mortgage
Home-page: UNKNOWN
Author: Luc De Backer
Author-email: luc_debacker@yahoo.com
License: UNKNOWN
Platform: UNKNOWN
Classifier: Programming Language :: Python :: 3
Classifier: License :: OSI Approved :: MIT License
Classifier: Operating System :: OS Independent
License-File: LICENCE.txt
